{
  "manual" : false,
  "urls" : {
    "-1713965985" : {
      "success" : {
        "timestamp" : "2024-07-20T03:55:06.342486190Z"
      },
      "error" : {
        "timestamp" : "2024-07-19T03:40:55.464171364Z",
        "code" : 403
      }
    },
    "1139205775" : {
      "error" : {
        "timestamp" : "2024-07-19T03:40:55.686317779Z",
        "code" : 403
      }
    },
    "-328186966" : {
      "error" : {
        "timestamp" : "2024-07-19T03:40:55.967325075Z",
        "code" : 403
      }
    }
  }
}