{
  "manual" : false,
  "urls" : {
    "797659770" : {
      "success" : {
        "timestamp" : "2023-07-07T03:46:05.688191Z"
      }
    },
    "293822310" : {
      "success" : {
        "timestamp" : "2023-07-07T03:46:06.480726Z"
      }
    },
    "132176070" : {
      "error" : {
        "timestamp" : "2025-03-22T03:58:37.011277161Z",
        "code" : 200
      }
    },
    "-1147687608" : {
      "error" : {
        "timestamp" : "2025-03-22T03:58:38.190228209Z",
        "code" : 200
      }
    },
    "-833734369" : {
      "error" : {
        "timestamp" : "2025-03-22T03:58:38.973767256Z",
        "code" : 200
      }
    },
    "-1520346210" : {
      "error" : {
        "timestamp" : "2025-03-22T03:58:39.775172692Z",
        "code" : 200
      }
    }
  }
}