{
  "manual" : false,
  "urls" : {
    "797659770" : {
      "success" : {
        "timestamp" : "2023-07-07T03:46:05.688191Z"
      }
    },
    "293822310" : {
      "success" : {
        "timestamp" : "2023-07-07T03:46:06.480726Z"
      }
    },
    "132176070" : {
      "error" : {
        "timestamp" : "2025-01-05T04:14:04.629067381Z",
        "code" : 200
      }
    },
    "-1147687608" : {
      "error" : {
        "timestamp" : "2025-01-05T04:14:13.912349171Z",
        "code" : 200
      }
    },
    "-833734369" : {
      "error" : {
        "timestamp" : "2025-01-05T04:14:19.190566254Z",
        "code" : 200
      }
    },
    "-1520346210" : {
      "error" : {
        "timestamp" : "2025-01-05T04:14:21.043281050Z",
        "code" : 200
      }
    }
  }
}