{
  "manual" : false,
  "urls" : {
    "59837387" : {
      "success" : {
        "timestamp" : "2023-04-28T07:44:21.515250Z"
      },
      "error" : {
        "timestamp" : "2024-07-19T03:43:17.203922017Z",
        "code" : 403
      }
    },
    "49444927" : { },
    "-1395983519" : {
      "error" : {
        "timestamp" : "2024-07-19T03:43:17.417563453Z",
        "code" : 403
      }
    },
    "1188060710" : {
      "error" : {
        "timestamp" : "2024-07-19T03:43:17.628703582Z",
        "code" : 403
      }
    }
  }
}