{
  "manual" : false,
  "urls" : {
    "-365876230" : {
      "success" : {
        "timestamp" : "2023-07-07T03:46:15.254101Z"
      }
    },
    "-16549658" : {
      "success" : {
        "timestamp" : "2023-07-07T03:46:15.477714Z"
      }
    },
    "-780914614" : {
      "error" : {
        "timestamp" : "2025-02-10T03:50:32.699108344Z",
        "code" : 200
      }
    },
    "-2060778292" : {
      "error" : {
        "timestamp" : "2025-02-10T03:50:33.376160221Z",
        "code" : 200
      }
    },
    "-1746825053" : {
      "error" : {
        "timestamp" : "2025-02-10T03:50:33.851690297Z",
        "code" : 200
      }
    },
    "213434266" : {
      "error" : {
        "timestamp" : "2025-02-10T03:50:34.128383788Z",
        "code" : 200
      }
    }
  }
}