{
  "manual" : false,
  "urls" : {
    "-365876230" : {
      "success" : {
        "timestamp" : "2023-07-07T03:46:15.254101Z"
      }
    },
    "-16549658" : {
      "success" : {
        "timestamp" : "2023-07-07T03:46:15.477714Z"
      }
    },
    "-780914614" : {
      "error" : {
        "timestamp" : "2025-06-07T04:26:33.978864823Z",
        "code" : 200
      }
    },
    "-2060778292" : {
      "error" : {
        "timestamp" : "2025-06-07T04:26:34.758537026Z",
        "code" : 200
      }
    },
    "-1746825053" : {
      "error" : {
        "timestamp" : "2025-06-07T04:26:35.444165904Z",
        "code" : 200
      }
    },
    "213434266" : {
      "error" : {
        "timestamp" : "2025-06-07T04:26:35.655007447Z",
        "code" : 200
      }
    }
  }
}