{
  "manual" : false,
  "urls" : {
    "-365876230" : {
      "success" : {
        "timestamp" : "2023-07-07T03:46:15.254101Z"
      }
    },
    "-16549658" : {
      "success" : {
        "timestamp" : "2023-07-07T03:46:15.477714Z"
      }
    },
    "-780914614" : {
      "error" : {
        "timestamp" : "2025-03-24T04:02:05.196073344Z",
        "code" : 200
      }
    },
    "-2060778292" : {
      "error" : {
        "timestamp" : "2025-03-24T04:02:06.025812041Z",
        "code" : 200
      }
    },
    "-1746825053" : {
      "error" : {
        "timestamp" : "2025-03-24T04:02:06.409146574Z",
        "code" : 200
      }
    },
    "213434266" : {
      "error" : {
        "timestamp" : "2025-03-24T04:02:06.639615527Z",
        "code" : 200
      }
    }
  }
}