{
  "manual" : false,
  "urls" : {
    "-365876230" : {
      "success" : {
        "timestamp" : "2023-07-07T03:46:15.254101Z"
      }
    },
    "-16549658" : {
      "success" : {
        "timestamp" : "2023-07-07T03:46:15.477714Z"
      }
    },
    "-780914614" : {
      "error" : {
        "timestamp" : "2025-03-14T04:00:31.055376333Z",
        "code" : 200
      }
    },
    "-2060778292" : {
      "error" : {
        "timestamp" : "2025-03-14T04:00:32.532933969Z",
        "code" : 200
      }
    },
    "-1746825053" : {
      "error" : {
        "timestamp" : "2025-03-14T04:00:33.042378066Z",
        "code" : 200
      }
    },
    "213434266" : {
      "error" : {
        "timestamp" : "2025-03-14T04:00:33.477077487Z",
        "code" : 200
      }
    }
  }
}