{
  "manual" : false,
  "urls" : {
    "1542933168" : {
      "success" : {
        "timestamp" : "2025-04-02T03:46:56.386312107Z"
      },
      "error" : {
        "timestamp" : "2025-04-01T04:33:27.538423205Z",
        "code" : -1
      }
    },
    "1873582383" : {
      "error" : {
        "timestamp" : "2025-04-05T03:49:53.390233542Z",
        "code" : 200
      }
    },
    "593718705" : {
      "error" : {
        "timestamp" : "2025-04-05T03:49:53.729049644Z",
        "code" : 200
      }
    },
    "-686144973" : {
      "error" : {
        "timestamp" : "2025-04-05T03:49:54.062781918Z",
        "code" : 200
      }
    }
  }
}