{
  "manual" : false,
  "urls" : {
    "401058300" : {
      "success" : {
        "timestamp" : "2023-07-07T03:46:20.886706Z"
      }
    },
    "622159272" : {
      "success" : {
        "timestamp" : "2023-07-07T03:46:21.116569Z"
      }
    },
    "1292492963" : {
      "error" : {
        "timestamp" : "2025-01-06T04:08:45.517268353Z",
        "code" : 200
      }
    },
    "1606446202" : {
      "error" : {
        "timestamp" : "2025-01-06T04:08:47.896329565Z",
        "code" : 200
      }
    },
    "-1858738717" : {
      "error" : {
        "timestamp" : "2025-01-06T04:08:49.559058047Z",
        "code" : 200
      }
    }
  }
}