{
  "manual" : false,
  "urls" : {
    "520804186" : {
      "success" : {
        "timestamp" : "2023-07-07T03:46:57.239307Z"
      }
    },
    "125514822" : {
      "success" : {
        "timestamp" : "2024-11-04T03:52:11.384887333Z"
      },
      "error" : {
        "timestamp" : "2024-11-03T04:08:09.275254972Z",
        "code" : -1
      }
    },
    "-1000572378" : {
      "error" : {
        "timestamp" : "2024-12-16T04:22:07.198186992Z",
        "code" : 200
      }
    },
    "2014531240" : {
      "error" : {
        "timestamp" : "2024-12-16T04:22:08.715699425Z",
        "code" : 200
      }
    },
    "-1966482817" : {
      "error" : {
        "timestamp" : "2024-12-16T04:22:09.851806297Z",
        "code" : 200
      }
    },
    "-1528254914" : {
      "error" : {
        "timestamp" : "2024-12-16T04:22:10.311972732Z",
        "code" : 200
      }
    }
  }
}