{
  "manual" : false,
  "urls" : {
    "2133425076" : {
      "success" : {
        "timestamp" : "2024-11-04T03:52:25.383978351Z"
      },
      "error" : {
        "timestamp" : "2024-11-03T04:12:02.178735009Z",
        "code" : -1
      }
    },
    "114048907" : {
      "error" : {
        "timestamp" : "2024-12-26T04:09:45.430372537Z",
        "code" : 200
      }
    },
    "428002146" : {
      "error" : {
        "timestamp" : "2024-12-26T04:09:46.296995385Z",
        "code" : 200
      }
    },
    "-851861532" : {
      "error" : {
        "timestamp" : "2024-12-26T04:09:46.780915913Z",
        "code" : 200
      }
    }
  }
}