{
  "manual" : false,
  "urls" : {
    "-1119557512" : {
      "success" : {
        "timestamp" : "2025-07-05T03:27:31.833756186Z"
      },
      "error" : {
        "timestamp" : "2025-07-04T03:30:47.731645048Z",
        "code" : 503
      }
    },
    "-351371680" : {
      "success" : {
        "timestamp" : "2023-05-23T03:08:40.356584Z"
      }
    },
    "919822996" : {
      "success" : {
        "timestamp" : "2025-07-08T03:32:05.253215382Z"
      },
      "error" : {
        "timestamp" : "2025-07-24T03:36:44.148230197Z",
        "code" : 503
      }
    }
  }
}