{
  "manual" : false,
  "urls" : {
    "1697973990" : {
      "success" : {
        "timestamp" : "2023-07-07T03:47:02.011855Z"
      }
    },
    "560152922" : {
      "error" : {
        "timestamp" : "2025-06-10T04:22:46.861688321Z",
        "code" : 200
      }
    },
    "-719710756" : {
      "error" : {
        "timestamp" : "2025-06-10T04:22:47.215233648Z",
        "code" : 200
      }
    },
    "-1999574434" : {
      "error" : {
        "timestamp" : "2025-06-10T04:22:47.545671676Z",
        "code" : 200
      }
    }
  }
}