{
  "manual" : false,
  "urls" : {
    "1697973990" : {
      "success" : {
        "timestamp" : "2023-07-07T03:47:02.011855Z"
      }
    },
    "560152922" : {
      "error" : {
        "timestamp" : "2025-07-26T04:26:57.463112307Z",
        "code" : 200
      }
    },
    "-719710756" : {
      "error" : {
        "timestamp" : "2025-07-26T04:26:58.244536161Z",
        "code" : 200
      }
    },
    "-1999574434" : {
      "error" : {
        "timestamp" : "2025-07-26T04:26:58.807909393Z",
        "code" : 200
      }
    }
  }
}