{
  "manual" : false,
  "urls" : {
    "1697973990" : {
      "success" : {
        "timestamp" : "2023-07-07T03:47:02.011855Z"
      }
    },
    "560152922" : {
      "error" : {
        "timestamp" : "2025-05-24T04:06:39.749428814Z",
        "code" : 200
      }
    },
    "-719710756" : {
      "error" : {
        "timestamp" : "2025-05-24T04:06:40.197727591Z",
        "code" : 200
      }
    },
    "-1999574434" : {
      "error" : {
        "timestamp" : "2025-05-24T04:06:40.569416824Z",
        "code" : 200
      }
    }
  }
}