{
  "manual" : false,
  "urls" : {
    "-2116832512" : {
      "success" : {
        "timestamp" : "2024-12-05T03:59:08.272157261Z"
      }
    },
    "-1639293476" : {
      "success" : {
        "timestamp" : "2024-12-05T03:59:08.750755187Z"
      }
    },
    "198082113" : {
      "success" : {
        "timestamp" : "2024-12-05T03:59:09.908879045Z"
      }
    },
    "1375810142" : {
      "error" : {
        "timestamp" : "2025-01-06T04:03:44.926663425Z",
        "code" : 200
      }
    },
    "95946464" : {
      "error" : {
        "timestamp" : "2025-01-06T04:03:46.981788883Z",
        "code" : 200
      }
    }
  }
}