{
  "manual" : false,
  "urls" : {
    "1441977259" : {
      "success" : {
        "timestamp" : "2023-04-28T07:42:04.186835Z"
      },
      "error" : {
        "timestamp" : "2024-07-19T03:42:50.738227015Z",
        "code" : 403
      }
    },
    "49443968" : { },
    "-426601535" : {
      "error" : {
        "timestamp" : "2024-07-19T03:42:50.941657391Z",
        "code" : 403
      }
    },
    "-598543674" : {
      "error" : {
        "timestamp" : "2024-07-19T03:42:51.136200001Z",
        "code" : 403
      }
    }
  }
}