{
  "manual" : false,
  "urls" : {
    "-886450773" : {
      "success" : {
        "timestamp" : "2025-01-30T03:07:56.060426396Z"
      },
      "error" : {
        "timestamp" : "2025-01-29T03:08:02.957047442Z",
        "code" : 503
      }
    },
    "-597631667" : {
      "success" : {
        "timestamp" : "2025-02-07T03:10:33.484650297Z"
      },
      "error" : {
        "timestamp" : "2025-02-06T03:09:37.642984268Z",
        "code" : 503
      }
    },
    "1758626561" : {
      "success" : {
        "timestamp" : "2023-05-23T03:08:18.566213Z"
      }
    }
  }
}