{
  "manual" : false,
  "urls" : {
    "737565970" : {
      "success" : {
        "timestamp" : "2024-05-21T03:09:35.906982442Z"
      }
    },
    "-1389444317" : {
      "success" : {
        "timestamp" : "2024-05-21T03:09:36.056722537Z"
      }
    },
    "-2082926202" : {
      "success" : {
        "timestamp" : "2024-11-21T03:16:00.809443970Z"
      },
      "error" : {
        "timestamp" : "2024-11-20T03:16:13.496547319Z",
        "code" : 503
      }
    },
    "1949561530" : {
      "success" : {
        "timestamp" : "2024-05-21T03:09:36.402613431Z"
      }
    }
  }
}