{
  "manual" : false,
  "urls" : {
    "577592050" : {
      "success" : {
        "timestamp" : "2023-05-23T03:07:28.277163Z"
      },
      "error" : {
        "timestamp" : "2024-12-15T03:26:46.930560813Z",
        "code" : 503
      }
    },
    "-286226109" : {
      "success" : {
        "timestamp" : "2023-05-23T03:07:28.541103Z"
      }
    },
    "280160166" : {
      "success" : {
        "timestamp" : "2023-05-23T03:07:28.793203Z"
      }
    },
    "-1242187558" : {
      "success" : {
        "timestamp" : "2023-05-23T03:07:29.031777Z"
      }
    }
  }
}