{
  "manual" : false,
  "urls" : {
    "-179199566" : {
      "success" : {
        "timestamp" : "2023-07-07T03:45:58.725437Z"
      }
    },
    "625424677" : {
      "error" : {
        "timestamp" : "2024-10-19T03:49:44.464966936Z",
        "code" : 200
      }
    },
    "-654439001" : {
      "error" : {
        "timestamp" : "2024-10-19T03:49:44.937574858Z",
        "code" : 200
      }
    },
    "-340485762" : {
      "error" : {
        "timestamp" : "2024-10-19T03:49:45.278396603Z",
        "code" : 200
      }
    }
  }
}