{
  "manual" : false,
  "urls" : {
    "-431539575" : {
      "success" : {
        "timestamp" : "2023-08-29T12:50:06.168000046Z"
      }
    },
    "-218804402" : {
      "error" : {
        "timestamp" : "2024-11-29T04:11:49.237189079Z",
        "code" : 200
      }
    },
    "-1498668080" : {
      "error" : {
        "timestamp" : "2024-11-29T04:11:50.821872164Z",
        "code" : 200
      }
    },
    "1516435538" : {
      "error" : {
        "timestamp" : "2024-11-29T04:11:51.795474923Z",
        "code" : 200
      }
    }
  }
}