{
  "manual" : false,
  "urls" : {
    "-431539575" : {
      "success" : {
        "timestamp" : "2023-08-29T12:50:06.168000046Z"
      }
    },
    "-1229423567" : {
      "error" : {
        "timestamp" : "2025-01-20T04:11:54.927560754Z",
        "code" : 200
      }
    },
    "1785680051" : {
      "error" : {
        "timestamp" : "2025-01-20T04:11:57.061613876Z",
        "code" : 200
      }
    },
    "505816373" : {
      "error" : {
        "timestamp" : "2025-01-20T04:11:58.641106637Z",
        "code" : 200
      }
    }
  }
}