{
  "manual" : false,
  "urls" : {
    "-431539575" : {
      "success" : {
        "timestamp" : "2023-08-29T12:50:06.168000046Z"
      }
    },
    "-218804402" : {
      "error" : {
        "timestamp" : "2024-11-05T04:04:32.593556419Z",
        "code" : 200
      }
    },
    "-1498668080" : {
      "error" : {
        "timestamp" : "2024-11-05T04:04:33.637516362Z",
        "code" : 200
      }
    },
    "1516435538" : {
      "error" : {
        "timestamp" : "2024-11-05T04:04:34.727686945Z",
        "code" : 200
      }
    }
  }
}