{
  "manual" : false,
  "urls" : {
    "286080814" : {
      "success" : {
        "timestamp" : "2023-08-29T12:50:05.383326076Z"
      }
    },
    "-1605913639" : {
      "error" : {
        "timestamp" : "2025-07-22T04:30:00.710319595Z",
        "code" : 200
      }
    },
    "1409189979" : {
      "error" : {
        "timestamp" : "2025-07-22T04:30:01.580148199Z",
        "code" : 200
      }
    },
    "129326301" : {
      "error" : {
        "timestamp" : "2025-07-22T04:30:02.323933822Z",
        "code" : 200
      }
    }
  }
}