{
  "manual" : false,
  "urls" : {
    "-1529582158" : {
      "success" : {
        "timestamp" : "2025-02-05T03:13:51.420192174Z"
      },
      "error" : {
        "timestamp" : "2025-02-04T03:12:50.710327106Z",
        "code" : 503
      }
    },
    "1308368515" : {
      "success" : {
        "timestamp" : "2023-12-08T03:09:50.612073880Z"
      }
    },
    "358292710" : {
      "success" : {
        "timestamp" : "2023-12-08T03:09:50.822588997Z"
      },
      "error" : {
        "timestamp" : "2025-02-05T03:13:51.542442080Z",
        "code" : 503
      }
    },
    "352407066" : {
      "success" : {
        "timestamp" : "2023-12-08T03:09:50.949529742Z"
      }
    }
  }
}