{
  "manual" : false,
  "urls" : {
    "691119995" : {
      "success" : {
        "timestamp" : "2023-04-28T07:20:16.392419Z"
      }
    },
    "-2003464003" : {
      "success" : {
        "timestamp" : "2024-10-11T16:40:50.867588589Z"
      }
    },
    "-644858390" : {
      "success" : {
        "timestamp" : "2024-10-11T16:40:47.113620344Z"
      }
    },
    "1974298374" : {
      "success" : {
        "timestamp" : "2023-07-26T03:41:09.017879Z"
      }
    },
    "2024362265" : {
      "success" : {
        "timestamp" : "2023-07-26T03:41:09.303276Z"
      }
    }
  }
}