{
  "manual" : false,
  "urls" : {
    "-1999434311" : {
      "success" : {
        "timestamp" : "2024-06-12T03:28:53.299745454Z"
      }
    },
    "-1142031947" : {
      "success" : {
        "timestamp" : "2024-06-12T03:28:54.180879329Z"
      }
    },
    "1878548082" : {
      "success" : {
        "timestamp" : "2024-06-12T03:29:12.423228818Z"
      }
    },
    "881892540" : {
      "success" : {
        "timestamp" : "2024-06-12T03:29:23.661241955Z"
      }
    },
    "-1739736801" : {
      "success" : {
        "timestamp" : "2024-06-12T03:29:48.163451902Z"
      }
    }
  }
}