{
  "manual" : false,
  "urls" : {
    "-1317993870" : {
      "success" : {
        "timestamp" : "2023-07-07T03:46:47.137130Z"
      }
    },
    "809941288" : {
      "error" : {
        "timestamp" : "2025-01-03T04:10:09.213197980Z",
        "code" : 200
      }
    },
    "1123894527" : {
      "error" : {
        "timestamp" : "2025-01-03T04:10:10.869943106Z",
        "code" : 200
      }
    },
    "-155969151" : {
      "error" : {
        "timestamp" : "2025-01-03T04:10:12.621361503Z",
        "code" : 200
      }
    }
  }
}