{
  "manual" : false,
  "urls" : {
    "-1317993870" : {
      "success" : {
        "timestamp" : "2023-07-07T03:46:47.137130Z"
      }
    },
    "809941288" : {
      "error" : {
        "timestamp" : "2025-02-12T03:59:51.578939528Z",
        "code" : 200
      }
    },
    "1123894527" : {
      "error" : {
        "timestamp" : "2025-02-12T03:59:52.370534506Z",
        "code" : 200
      }
    },
    "-155969151" : {
      "error" : {
        "timestamp" : "2025-02-12T03:59:53.025041572Z",
        "code" : 200
      }
    }
  }
}