{
  "manual" : false,
  "urls" : {
    "2010754074" : {
      "success" : {
        "timestamp" : "2023-07-07T03:46:35.775130Z"
      }
    },
    "642984198" : {
      "success" : {
        "timestamp" : "2024-11-04T03:52:08.142563732Z"
      },
      "error" : {
        "timestamp" : "2024-11-03T04:06:46.607582931Z",
        "code" : -1
      }
    },
    "2137858668" : {
      "error" : {
        "timestamp" : "2025-01-28T03:52:12.537271861Z",
        "code" : 200
      }
    },
    "857994990" : {
      "error" : {
        "timestamp" : "2025-01-28T03:52:13.627320469Z",
        "code" : 200
      }
    },
    "1171948229" : {
      "error" : {
        "timestamp" : "2025-01-28T03:52:14.173417546Z",
        "code" : 200
      }
    },
    "1016758072" : {
      "error" : {
        "timestamp" : "2025-01-28T03:52:14.579704681Z",
        "code" : 200
      }
    }
  }
}