{
  "manual" : false,
  "urls" : {
    "1861118255" : {
      "success" : {
        "timestamp" : "2023-10-04T03:39:24.650442852Z"
      }
    },
    "-1245625011" : {
      "success" : {
        "timestamp" : "2023-10-04T03:39:25.428507940Z"
      }
    },
    "939344816" : {
      "success" : {
        "timestamp" : "2023-10-04T03:39:25.872915516Z"
      }
    },
    "162787362" : {
      "error" : {
        "timestamp" : "2024-12-10T04:00:35.185583025Z",
        "code" : 200
      }
    },
    "-1506511494" : {
      "error" : {
        "timestamp" : "2024-12-10T04:00:35.635393192Z",
        "code" : 200
      }
    },
    "1508592124" : {
      "error" : {
        "timestamp" : "2024-12-10T04:00:36.202561856Z",
        "code" : 200
      }
    },
    "228728446" : {
      "error" : {
        "timestamp" : "2024-12-10T04:00:36.669500762Z",
        "code" : 200
      }
    },
    "459521251" : {
      "error" : {
        "timestamp" : "2024-12-10T04:00:36.930860702Z",
        "code" : 200
      }
    }
  }
}