{
  "manual" : false,
  "urls" : {
    "-843821638" : {
      "success" : {
        "timestamp" : "2023-07-07T03:46:56.978043Z"
      }
    },
    "1121663654" : {
      "success" : {
        "timestamp" : "2023-07-07T03:46:57.176118Z"
      }
    },
    "-155103225" : {
      "error" : {
        "timestamp" : "2024-11-14T04:05:47.287672259Z",
        "code" : 200
      }
    },
    "-1434966903" : {
      "error" : {
        "timestamp" : "2024-11-14T04:05:47.725639268Z",
        "code" : 200
      }
    },
    "-1121013664" : {
      "error" : {
        "timestamp" : "2024-11-14T04:05:48.121639659Z",
        "code" : 200
      }
    },
    "-21067971" : {
      "error" : {
        "timestamp" : "2024-11-14T04:05:48.375157262Z",
        "code" : 200
      }
    }
  }
}