{
  "manual" : false,
  "urls" : {
    "-843821638" : {
      "success" : {
        "timestamp" : "2023-07-07T03:46:56.978043Z"
      }
    },
    "1121663654" : {
      "success" : {
        "timestamp" : "2023-07-07T03:46:57.176118Z"
      }
    },
    "-155103225" : {
      "error" : {
        "timestamp" : "2025-02-01T04:09:26.735793230Z",
        "code" : 200
      }
    },
    "-1434966903" : {
      "error" : {
        "timestamp" : "2025-02-01T04:09:29.553292102Z",
        "code" : 200
      }
    },
    "-1121013664" : {
      "error" : {
        "timestamp" : "2025-02-01T04:09:31.189884848Z",
        "code" : 200
      }
    },
    "-21067971" : {
      "error" : {
        "timestamp" : "2025-02-01T04:09:32.101851582Z",
        "code" : 200
      }
    }
  }
}