{
  "manual" : false,
  "urls" : {
    "1289876726" : {
      "success" : {
        "timestamp" : "2023-07-07T03:46:48.408066Z"
      }
    },
    "1528271350" : {
      "error" : {
        "timestamp" : "2025-01-17T03:49:30.265915086Z",
        "code" : 200
      }
    },
    "1842224589" : {
      "error" : {
        "timestamp" : "2025-01-17T03:49:31.243337192Z",
        "code" : 200
      }
    },
    "562360911" : {
      "error" : {
        "timestamp" : "2025-01-17T03:49:31.832743318Z",
        "code" : 200
      }
    }
  }
}