{
  "manual" : false,
  "urls" : {
    "446328376" : {
      "success" : {
        "timestamp" : "2023-07-07T03:46:47.453438Z"
      }
    },
    "-1763097012" : {
      "error" : {
        "timestamp" : "2024-11-25T04:20:56.763215650Z",
        "code" : 200
      }
    },
    "-1449143773" : {
      "error" : {
        "timestamp" : "2024-11-25T04:20:59.281766421Z",
        "code" : 200
      }
    },
    "1565959845" : {
      "error" : {
        "timestamp" : "2024-11-25T04:21:01.825584509Z",
        "code" : 200
      }
    }
  }
}