{
  "manual" : false,
  "urls" : {
    "-2132681702" : {
      "success" : {
        "timestamp" : "2023-07-07T03:46:00.759638Z"
      }
    },
    "-702326522" : {
      "success" : {
        "timestamp" : "2023-07-07T03:46:01.739800Z"
      }
    },
    "-713293083" : {
      "error" : {
        "timestamp" : "2024-10-24T04:03:12.002154965Z",
        "code" : 200
      }
    },
    "-1993156761" : {
      "error" : {
        "timestamp" : "2024-10-24T04:03:14.480560921Z",
        "code" : 200
      }
    },
    "-1679203522" : {
      "error" : {
        "timestamp" : "2024-10-24T04:03:15.563031396Z",
        "code" : 200
      }
    },
    "1267434143" : {
      "error" : {
        "timestamp" : "2024-10-24T04:03:16.855138377Z",
        "code" : 200
      }
    }
  }
}