{
  "manual" : false,
  "urls" : {
    "-2132681702" : {
      "success" : {
        "timestamp" : "2023-07-07T03:46:00.759638Z"
      }
    },
    "-702326522" : {
      "success" : {
        "timestamp" : "2023-07-07T03:46:01.739800Z"
      }
    },
    "-713293083" : {
      "error" : {
        "timestamp" : "2024-10-13T03:46:40.473763843Z",
        "code" : 200
      }
    },
    "-1993156761" : {
      "error" : {
        "timestamp" : "2024-10-13T03:46:41.021248108Z",
        "code" : 200
      }
    },
    "-1679203522" : {
      "error" : {
        "timestamp" : "2024-10-13T03:46:41.360642480Z",
        "code" : 200
      }
    },
    "1267434143" : {
      "error" : {
        "timestamp" : "2024-10-13T03:46:41.619776099Z",
        "code" : 200
      }
    }
  }
}