{
  "manual" : false,
  "urls" : {
    "-955302580" : {
      "success" : {
        "timestamp" : "2024-02-09T03:43:48.094429994Z"
      }
    },
    "1242374160" : {
      "success" : {
        "timestamp" : "2024-02-09T03:43:48.760640707Z"
      }
    },
    "-1646087795" : {
      "success" : {
        "timestamp" : "2024-02-09T03:43:49.042495766Z"
      }
    },
    "-1046535489" : {
      "error" : {
        "timestamp" : "2025-01-22T03:41:03.741868558Z",
        "code" : 200
      }
    },
    "2037080509" : {
      "error" : {
        "timestamp" : "2025-01-22T03:41:04.321465998Z",
        "code" : 200
      }
    },
    "757216831" : {
      "error" : {
        "timestamp" : "2025-01-22T03:41:05.091384047Z",
        "code" : 200
      }
    },
    "-522646847" : {
      "error" : {
        "timestamp" : "2025-01-22T03:41:05.525333641Z",
        "code" : 200
      }
    },
    "-1512281792" : {
      "error" : {
        "timestamp" : "2025-01-22T03:41:05.740712343Z",
        "code" : 200
      }
    }
  }
}