{
  "manual" : false,
  "urls" : {
    "-1613239824" : {
      "success" : {
        "timestamp" : "2023-07-07T03:46:51.528918Z"
      }
    },
    "255004381" : {
      "error" : {
        "timestamp" : "2025-07-19T04:20:08.963540321Z",
        "code" : 200
      }
    },
    "-1024859297" : {
      "error" : {
        "timestamp" : "2025-07-19T04:20:09.349821277Z",
        "code" : 200
      }
    },
    "1990244321" : {
      "error" : {
        "timestamp" : "2025-07-19T04:20:09.827443696Z",
        "code" : 200
      }
    }
  }
}