{
  "manual" : false,
  "urls" : {
    "-1613239824" : {
      "success" : {
        "timestamp" : "2023-07-07T03:46:51.528918Z"
      }
    },
    "255004381" : {
      "error" : {
        "timestamp" : "2024-12-23T03:44:45.266438344Z",
        "code" : 200
      }
    },
    "-1024859297" : {
      "error" : {
        "timestamp" : "2024-12-23T03:44:45.659123145Z",
        "code" : 200
      }
    },
    "1990244321" : {
      "error" : {
        "timestamp" : "2024-12-23T03:44:46.047834535Z",
        "code" : 200
      }
    }
  }
}