{
  "manual" : false,
  "urls" : {
    "1803143088" : {
      "success" : {
        "timestamp" : "2025-04-02T03:46:44.829455880Z"
      },
      "error" : {
        "timestamp" : "2025-04-01T04:27:52.017963865Z",
        "code" : -1
      }
    },
    "1964694879" : {
      "error" : {
        "timestamp" : "2025-04-14T03:54:25.145958729Z",
        "code" : 200
      }
    },
    "684831201" : {
      "error" : {
        "timestamp" : "2025-04-14T03:54:25.501615968Z",
        "code" : 200
      }
    },
    "998784440" : {
      "error" : {
        "timestamp" : "2025-04-14T03:54:25.840530801Z",
        "code" : 200
      }
    }
  }
}