{
  "manual" : false,
  "urls" : {
    "-642731814" : {
      "success" : {
        "timestamp" : "2023-07-07T03:46:59.912394Z"
      }
    },
    "-184857146" : {
      "success" : {
        "timestamp" : "2023-07-07T03:47:00.144317Z"
      }
    },
    "1343405510" : {
      "error" : {
        "timestamp" : "2025-01-19T03:51:03.072231390Z",
        "code" : 200
      }
    },
    "1657358749" : {
      "error" : {
        "timestamp" : "2025-01-19T03:51:03.550280662Z",
        "code" : 200
      }
    },
    "270542176" : {
      "error" : {
        "timestamp" : "2025-01-19T03:51:03.867546510Z",
        "code" : 200
      }
    }
  }
}