{
  "manual" : false,
  "urls" : {
    "-769691474" : {
      "success" : {
        "timestamp" : "2023-07-07T03:46:52.682410Z"
      }
    },
    "976581267" : {
      "error" : {
        "timestamp" : "2025-03-03T03:57:39.636400589Z",
        "code" : 200
      }
    },
    "-303282411" : {
      "error" : {
        "timestamp" : "2025-03-03T03:57:40.712987179Z",
        "code" : 200
      }
    },
    "-1583146089" : {
      "error" : {
        "timestamp" : "2025-03-03T03:57:41.708856938Z",
        "code" : 200
      }
    }
  }
}