{
  "manual" : false,
  "urls" : {
    "-769691474" : {
      "success" : {
        "timestamp" : "2023-07-07T03:46:52.682410Z"
      }
    },
    "976581267" : {
      "error" : {
        "timestamp" : "2025-02-01T04:06:39.042218317Z",
        "code" : 200
      }
    },
    "-303282411" : {
      "error" : {
        "timestamp" : "2025-02-01T04:06:40.181015926Z",
        "code" : 200
      }
    },
    "-1583146089" : {
      "error" : {
        "timestamp" : "2025-02-01T04:06:41.138492317Z",
        "code" : 200
      }
    }
  }
}