{
  "manual" : false,
  "urls" : {
    "-769691474" : {
      "success" : {
        "timestamp" : "2023-07-07T03:46:52.682410Z"
      }
    },
    "976581267" : {
      "error" : {
        "timestamp" : "2024-12-22T03:52:45.921758194Z",
        "code" : 200
      }
    },
    "-303282411" : {
      "error" : {
        "timestamp" : "2024-12-22T03:52:46.413858860Z",
        "code" : 200
      }
    },
    "-1583146089" : {
      "error" : {
        "timestamp" : "2024-12-22T03:52:46.784952283Z",
        "code" : 200
      }
    }
  }
}