{
  "manual" : false,
  "urls" : {
    "1074515354" : {
      "success" : {
        "timestamp" : "2023-07-07T03:46:19.406606Z"
      }
    },
    "462129798" : {
      "success" : {
        "timestamp" : "2023-07-07T03:46:19.679139Z"
      }
    },
    "-464028317" : {
      "error" : {
        "timestamp" : "2024-10-15T03:51:49.421704651Z",
        "code" : 200
      }
    },
    "-1743891995" : {
      "error" : {
        "timestamp" : "2024-10-15T03:51:50.369173056Z",
        "code" : 200
      }
    },
    "-1429938756" : {
      "error" : {
        "timestamp" : "2024-10-15T03:51:51.123431303Z",
        "code" : 200
      }
    },
    "1005232737" : {
      "error" : {
        "timestamp" : "2024-10-15T03:51:51.616703071Z",
        "code" : 200
      }
    }
  }
}