{
  "manual" : false,
  "urls" : {
    "1074515354" : {
      "success" : {
        "timestamp" : "2023-07-07T03:46:19.406606Z"
      }
    },
    "462129798" : {
      "success" : {
        "timestamp" : "2023-07-07T03:46:19.679139Z"
      }
    },
    "-464028317" : {
      "error" : {
        "timestamp" : "2024-11-26T04:12:10.975303195Z",
        "code" : 200
      }
    },
    "-1743891995" : {
      "error" : {
        "timestamp" : "2024-11-26T04:12:13.495674458Z",
        "code" : 200
      }
    },
    "-1429938756" : {
      "error" : {
        "timestamp" : "2024-11-26T04:12:14.955769975Z",
        "code" : 200
      }
    },
    "1005232737" : {
      "error" : {
        "timestamp" : "2024-11-26T04:12:15.950449312Z",
        "code" : 200
      }
    }
  }
}