{
  "manual" : false,
  "urls" : {
    "2036961530" : {
      "success" : {
        "timestamp" : "2023-07-07T03:46:18.492004Z"
      }
    },
    "2079022566" : {
      "success" : {
        "timestamp" : "2023-07-07T03:46:18.719404Z"
      }
    },
    "1317079776" : {
      "error" : {
        "timestamp" : "2025-08-01T04:33:12.254840447Z",
        "code" : 200
      }
    },
    "1631033015" : {
      "error" : {
        "timestamp" : "2025-08-01T04:33:12.776284419Z",
        "code" : 200
      }
    },
    "774099718" : {
      "error" : {
        "timestamp" : "2025-08-01T04:33:12.990897723Z",
        "code" : 200
      }
    }
  }
}