{
  "manual" : false,
  "urls" : {
    "-1440974832" : {
      "success" : {
        "timestamp" : "2024-03-22T03:49:58.790128554Z"
      }
    },
    "593081116" : {
      "error" : {
        "timestamp" : "2024-11-01T04:07:55.779896894Z",
        "code" : 200
      }
    },
    "-686782562" : {
      "error" : {
        "timestamp" : "2024-11-01T04:07:56.794120449Z",
        "code" : 200
      }
    },
    "-1966646240" : {
      "error" : {
        "timestamp" : "2024-11-01T04:07:59.325975004Z",
        "code" : 200
      }
    }
  }
}