{
  "manual" : false,
  "urls" : {
    "-2056915942" : {
      "success" : {
        "timestamp" : "2023-07-07T03:46:16.840056Z"
      }
    },
    "772501766" : {
      "success" : {
        "timestamp" : "2025-04-02T03:46:51.217252242Z"
      },
      "error" : {
        "timestamp" : "2025-04-01T04:31:21.163149961Z",
        "code" : -1
      }
    },
    "857878117" : {
      "error" : {
        "timestamp" : "2025-05-03T04:03:30.765754398Z",
        "code" : 200
      }
    },
    "-421985561" : {
      "error" : {
        "timestamp" : "2025-05-03T04:03:31.341026824Z",
        "code" : 200
      }
    },
    "-108032322" : {
      "error" : {
        "timestamp" : "2025-05-03T04:03:31.709236641Z",
        "code" : 200
      }
    },
    "-274831585" : {
      "error" : {
        "timestamp" : "2025-05-03T04:03:32.097365609Z",
        "code" : 200
      }
    }
  }
}