{
  "manual" : false,
  "urls" : {
    "518323353" : {
      "success" : {
        "timestamp" : "2023-04-28T07:46:52.281633Z"
      },
      "error" : {
        "timestamp" : "2024-07-19T03:43:46.367517629Z",
        "code" : 403
      }
    },
    "1532822607" : { },
    "536252629" : {
      "error" : {
        "timestamp" : "2024-07-19T03:43:46.520939799Z",
        "code" : 403
      }
    },
    "-1708232016" : {
      "error" : {
        "timestamp" : "2024-07-19T03:43:46.701974844Z",
        "code" : 403
      }
    }
  }
}