{
  "manual" : false,
  "urls" : {
    "-1855826118" : {
      "success" : {
        "timestamp" : "2023-07-07T03:46:19.997567Z"
      }
    },
    "-534019034" : {
      "success" : {
        "timestamp" : "2023-07-07T03:46:20.288256Z"
      }
    },
    "-153196962" : {
      "error" : {
        "timestamp" : "2024-10-22T04:05:26.155072458Z",
        "code" : 200
      }
    },
    "-1433060640" : {
      "error" : {
        "timestamp" : "2024-10-22T04:05:29.394728608Z",
        "code" : 200
      }
    },
    "-1119107401" : {
      "error" : {
        "timestamp" : "2024-10-22T04:05:31.873465011Z",
        "code" : 200
      }
    },
    "-1852202234" : {
      "error" : {
        "timestamp" : "2024-10-22T04:05:33.541283345Z",
        "code" : 200
      }
    }
  }
}