{
  "manual" : false,
  "urls" : {
    "-1363007155" : {
      "success" : {
        "timestamp" : "2023-12-09T03:41:07.436993485Z"
      }
    },
    "1482893423" : {
      "success" : {
        "timestamp" : "2023-12-09T03:41:07.923153368Z"
      }
    },
    "-785190322" : {
      "success" : {
        "timestamp" : "2023-12-09T03:41:08.201156597Z"
      }
    },
    "239388634" : {
      "error" : {
        "timestamp" : "2025-05-14T04:24:45.243360306Z",
        "code" : 200
      }
    },
    "-105651518" : {
      "error" : {
        "timestamp" : "2025-05-14T04:24:46.496793812Z",
        "code" : 200
      }
    },
    "-1385515196" : {
      "error" : {
        "timestamp" : "2025-05-14T04:24:47.283025689Z",
        "code" : 200
      }
    },
    "1629588422" : {
      "error" : {
        "timestamp" : "2025-05-14T04:24:47.924208591Z",
        "code" : 200
      }
    },
    "-1266762085" : {
      "error" : {
        "timestamp" : "2025-05-14T04:24:48.424574912Z",
        "code" : 200
      }
    }
  }
}