{
  "manual" : false,
  "urls" : {
    "1885430010" : {
      "success" : {
        "timestamp" : "2023-07-07T03:46:57.583741Z"
      }
    },
    "-870634010" : {
      "success" : {
        "timestamp" : "2023-07-07T03:46:57.834763Z"
      }
    },
    "1731574070" : {
      "error" : {
        "timestamp" : "2024-10-22T04:08:59.212997492Z",
        "code" : 200
      }
    },
    "451710392" : {
      "error" : {
        "timestamp" : "2024-10-22T04:09:01.848722841Z",
        "code" : 200
      }
    },
    "765663631" : {
      "error" : {
        "timestamp" : "2024-10-22T04:09:04.014371047Z",
        "code" : 200
      }
    },
    "1537817902" : {
      "error" : {
        "timestamp" : "2024-10-22T04:09:05.484293799Z",
        "code" : 200
      }
    }
  }
}