{
  "manual" : false,
  "urls" : {
    "-1165822822" : {
      "success" : {
        "timestamp" : "2025-01-17T03:46:21.049367042Z"
      },
      "error" : {
        "timestamp" : "2025-01-16T03:38:38.007653693Z",
        "code" : 403
      }
    },
    "1828815671" : {
      "error" : {
        "timestamp" : "2025-03-19T04:00:39.448095453Z",
        "code" : 200
      }
    },
    "548951993" : {
      "error" : {
        "timestamp" : "2025-03-19T04:00:40.136706254Z",
        "code" : 200
      }
    },
    "-730911685" : {
      "error" : {
        "timestamp" : "2025-03-19T04:00:41.574328240Z",
        "code" : 200
      }
    }
  }
}