{
  "manual" : false,
  "urls" : {
    "-2053157748" : {
      "success" : {
        "timestamp" : "2025-04-30T04:15:11.222999102Z"
      }
    },
    "-630480033" : {
      "success" : {
        "timestamp" : "2025-04-30T04:15:12.043142239Z"
      }
    },
    "1480397390" : {
      "success" : {
        "timestamp" : "2025-04-30T04:15:12.805249576Z"
      }
    },
    "-172363594" : {
      "success" : {
        "timestamp" : "2025-05-31T04:19:03.712390703Z"
      },
      "error" : {
        "timestamp" : "2025-05-30T03:59:19.353565526Z",
        "code" : -1
      }
    }
  }
}