{
  "manual" : false,
  "urls" : {
    "-1196014289" : {
      "success" : {
        "timestamp" : "2024-04-04T04:00:28.809346151Z"
      }
    },
    "-1499731635" : {
      "success" : {
        "timestamp" : "2024-04-04T04:00:31.338226954Z"
      }
    },
    "-69591120" : {
      "success" : {
        "timestamp" : "2024-04-04T04:00:32.551562461Z"
      }
    },
    "128587264" : {
      "error" : {
        "timestamp" : "2025-03-19T04:00:17.162245275Z",
        "code" : 200
      }
    },
    "1840585436" : {
      "error" : {
        "timestamp" : "2025-03-19T04:00:17.829901048Z",
        "code" : 200
      }
    },
    "560721758" : {
      "error" : {
        "timestamp" : "2025-03-19T04:00:18.475735652Z",
        "code" : 200
      }
    },
    "-719141920" : {
      "error" : {
        "timestamp" : "2025-03-19T04:00:19.159371949Z",
        "code" : 200
      }
    },
    "-1091886783" : {
      "error" : {
        "timestamp" : "2025-03-19T04:00:19.909629693Z",
        "code" : 200
      }
    }
  }
}