{
  "manual" : false,
  "urls" : {
    "699384818" : {
      "success" : {
        "timestamp" : "2024-11-04T03:52:22.281100529Z"
      },
      "error" : {
        "timestamp" : "2024-11-03T04:10:58.821071862Z",
        "code" : -1
      }
    },
    "-1053997112" : {
      "error" : {
        "timestamp" : "2025-02-12T03:58:06.896201918Z",
        "code" : 200
      }
    },
    "1961106506" : {
      "error" : {
        "timestamp" : "2025-02-12T03:58:07.589653617Z",
        "code" : 200
      }
    },
    "681242828" : {
      "error" : {
        "timestamp" : "2025-02-12T03:58:08.243282677Z",
        "code" : 200
      }
    }
  }
}