{
  "manual" : false,
  "urls" : {
    "795544512" : {
      "success" : {
        "timestamp" : "2023-12-06T03:45:28.154435986Z"
      }
    },
    "-1649717988" : {
      "success" : {
        "timestamp" : "2023-12-06T03:45:28.591560188Z"
      }
    },
    "822568705" : {
      "success" : {
        "timestamp" : "2023-12-06T03:45:28.868850618Z"
      }
    },
    "-1593289348" : {
      "error" : {
        "timestamp" : "2025-05-31T04:31:11.221841245Z",
        "code" : 200
      }
    },
    "208853472" : {
      "error" : {
        "timestamp" : "2025-05-31T04:31:15.105249478Z",
        "code" : 200
      }
    },
    "-1071010206" : {
      "error" : {
        "timestamp" : "2025-05-31T04:31:17.940336112Z",
        "code" : 200
      }
    },
    "1944093412" : {
      "error" : {
        "timestamp" : "2025-05-31T04:31:19.105579056Z",
        "code" : 200
      }
    },
    "1306373565" : {
      "error" : {
        "timestamp" : "2025-05-31T04:31:19.960154859Z",
        "code" : 200
      }
    }
  }
}